djcompiler/__init__.py
djcompiler/__main__.py
djcompiler/compiler/__init__.py
djcompiler/compiler/djcompiler.py
djcompiler/management/__init__.py
djcompiler/management/command/__init__.py
djcompiler/management/command/buildfile.py
djcompiler/management/command/buildpy.py
djcompiler/management/command/compile.py
djcompiler-0.0.5.dist-info/LICENSE
djcompiler-0.0.5.dist-info/METADATA
djcompiler-0.0.5.dist-info/WHEEL
djcompiler-0.0.5.dist-info/entry_points.txt
djcompiler-0.0.5.dist-info/top_level.txt
djcompiler-0.0.5.dist-info/RECORD
